{
  "annotations": { "list": [] },
  "editable": true,
  "fiscalYearStartMonth": 0,
  "graphTooltip": 0,
  "id": null,
  "links": [],
  "panels": [
    {
      "datasource": { "type": "prometheus", "uid": "prometheus" },
      "fieldConfig": { "defaults": {}, "overrides": [] },
      "gridPos": { "h": 8, "w": 12, "x": 0, "y": 0 },
      "id": 1,
      "options": { "legend": { "displayMode": "list", "placement": "bottom" } },
      "targets": [
        {
          "expr": "sum(rate(container_cpu_usage_seconds_total{container_label_com_docker_compose_project=\"poisk-istochnikov\",container_label_com_docker_compose_service!=\"\"}[5m])) by (container_label_com_docker_compose_service)",
          "legendFormat": "{{container_label_com_docker_compose_service}}",
          "refId": "A"
        }
      ],
      "title": "CPU usage (cores) by service",
      "type": "timeseries"
    },
    {
      "datasource": { "type": "prometheus", "uid": "prometheus" },
      "fieldConfig": { "defaults": {}, "overrides": [] },
      "gridPos": { "h": 8, "w": 12, "x": 12, "y": 0 },
      "id": 2,
      "options": { "legend": { "displayMode": "list", "placement": "bottom" } },
      "targets": [
        {
          "expr": "sum(container_memory_working_set_bytes{container_label_com_docker_compose_project=\"poisk-istochnikov\",container_label_com_docker_compose_service!=\"\"}) by (container_label_com_docker_compose_service) / 1024 / 1024",
          "legendFormat": "{{container_label_com_docker_compose_service}} MB",
          "refId": "A"
        }
      ],
      "title": "Memory working set (MB) by service",
      "type": "timeseries"
    },
    {
      "datasource": { "type": "prometheus", "uid": "prometheus" },
      "fieldConfig": { "defaults": {}, "overrides": [] },
      "gridPos": { "h": 8, "w": 12, "x": 0, "y": 8 },
      "id": 3,
      "options": { "legend": { "displayMode": "list", "placement": "bottom" } },
      "targets": [
        {
          "expr": "sum(rate(container_fs_reads_bytes_total{container_label_com_docker_compose_project=\"poisk-istochnikov\",container_label_com_docker_compose_service!=\"\"}[5m])) by (container_label_com_docker_compose_service)",
          "legendFormat": "{{container_label_com_docker_compose_service}}",
          "refId": "A"
        }
      ],
      "title": "Disk reads (bytes/s) by service",
      "type": "timeseries"
    },
    {
      "datasource": { "type": "prometheus", "uid": "prometheus" },
      "fieldConfig": { "defaults": {}, "overrides": [] },
      "gridPos": { "h": 8, "w": 12, "x": 12, "y": 8 },
      "id": 4,
      "options": { "legend": { "displayMode": "list", "placement": "bottom" } },
      "targets": [
        {
          "expr": "sum(rate(container_fs_writes_bytes_total{container_label_com_docker_compose_project=\"poisk-istochnikov\",container_label_com_docker_compose_service!=\"\"}[5m])) by (container_label_com_docker_compose_service)",
          "legendFormat": "{{container_label_com_docker_compose_service}}",
          "refId": "A"
        }
      ],
      "title": "Disk writes (bytes/s) by service",
      "type": "timeseries"
    }
  ],
  "refresh": "5s",
  "schemaVersion": 39,
  "style": "dark",
  "tags": ["infra"],
  "templating": { "list": [] },
  "time": { "from": "now-15m", "to": "now" },
  "timepicker": {},
  "timezone": "",
  "title": "Production / Infra",
  "uid": "poisk-infra",
  "version": 1
}

